jwt_knox/__init__.py
jwt_knox/apps.py
jwt_knox/auth.py
jwt_knox/migrations/__init__.py
jwt_knox/settings.py
jwt_knox/urls.py
jwt_knox/utils.py
jwt_knox/viewsets.py
drf_jwt_knox-0.2.0.dist-info/LICENSE
drf_jwt_knox-0.2.0.dist-info/METADATA
drf_jwt_knox-0.2.0.dist-info/WHEEL
drf_jwt_knox-0.2.0.dist-info/RECORD
