Metadata-Version: 2.1
Name: drf-jwt-knox
Version: 0.2.0
Summary: Knox-fortified JSON Web Tokens for Django REST Framework
License: Apache2
Author: Santiago Saavedra
Author-email: ssaavedra@gpul.org
Requires-Python: >=3.9,<4.0
Classifier: License :: Other/Proprietary License
Classifier: Programming Language :: Python :: 3
Classifier: Programming Language :: Python :: 3.9
Classifier: Programming Language :: Python :: 3.10
Classifier: Programming Language :: Python :: 3.11
Requires-Dist: PyJWT (>=2.7.0,<3.0.0)
Requires-Dist: django-rest-knox (>=4.2.0,<5.0.0)
Requires-Dist: djangorestframework (>=3.14,<4.0)
